illufly_tts/__init__.py
illufly_tts/__main__.py
illufly_tts/api/__init__.py
illufly_tts/api/endpoints.py
illufly_tts/api/mcp_client.py
illufly_tts/api/mcp_server.py
illufly_tts/core/__init__.py
illufly_tts/core/g2p/__init__.py
illufly_tts/core/g2p/base_g2p.py
illufly_tts/core/g2p/chinese_g2p.py
illufly_tts/core/g2p/data/__init__.py
illufly_tts/core/g2p/data/gb_gold.json
illufly_tts/core/g2p/data/gb_silver.json
illufly_tts/core/g2p/data/us_gold.json
illufly_tts/core/g2p/data/us_silver.json
illufly_tts/core/g2p/english_g2p.py
illufly_tts/core/g2p/token.py
illufly_tts/core/g2p/tone_sandhi.py
illufly_tts/core/g2p/transcription.py
illufly_tts/core/g2p/zh_frontend.py
illufly_tts/core/kmodel.py
illufly_tts/core/normalization/__init__.py
illufly_tts/core/normalization/en/__init__.py
illufly_tts/core/normalization/en/chronology.py
illufly_tts/core/normalization/en/constants.py
illufly_tts/core/normalization/en/currency.py
illufly_tts/core/normalization/en/num.py
illufly_tts/core/normalization/en/phone.py
illufly_tts/core/normalization/en/phonecode.py
illufly_tts/core/normalization/en/text_normalization.py
illufly_tts/core/normalization/zh/README.md
illufly_tts/core/normalization/zh/__init__.py
illufly_tts/core/normalization/zh/char_convert.py
illufly_tts/core/normalization/zh/chronology.py
illufly_tts/core/normalization/zh/constants.py
illufly_tts/core/normalization/zh/num.py
illufly_tts/core/normalization/zh/phonecode.py
illufly_tts/core/normalization/zh/quantifier.py
illufly_tts/core/normalization/zh/text_normalization.py
illufly_tts/core/pipeline.py
illufly_tts/core/resources/dictionaries/chinese_dict.txt
illufly_tts/core/resources/dictionaries/english_dict.txt
illufly_tts/core/service.py
illufly_tts-0.2.1.dist-info/METADATA
illufly_tts-0.2.1.dist-info/WHEEL
illufly_tts-0.2.1.dist-info/entry_points.txt
illufly_tts-0.2.1.dist-info/RECORD
