Metadata-Version: 2.1
Name: illufly-tts
Version: 0.2.1
Summary: Text-to-Speech module for Illufly AI
Author: arcstep
Author-email: 43801@qq.com
Requires-Python: >=3.11,<3.13
Classifier: Programming Language :: Python :: 3
Classifier: Programming Language :: Python :: 3.11
Classifier: Programming Language :: Python :: 3.12
Requires-Dist: aiofiles (>=0.8.0)
Requires-Dist: anyio (>=3.6.0)
Requires-Dist: click (>=8.0.0)
Requires-Dist: fastapi (>=0.68.0)
Requires-Dist: g2p-en (>=2.1.0)
Requires-Dist: jieba (>=0.42.1,<0.43.0)
Requires-Dist: kokoro (>=0.8.1)
Requires-Dist: langid (>=1.1.6)
Requires-Dist: loguru (>=0.5.3)
Requires-Dist: mcp (>=1.6.0,<2.0.0)
Requires-Dist: misaki[en] (>=0.8.1) ; python_version >= "3.11" and python_version < "3.13"
Requires-Dist: numpy (>=1.22.0,<2.0.0)
Requires-Dist: ordered-set (>=4.1.0)
Requires-Dist: phonemizer (>=3.3.0,<4.0.0)
Requires-Dist: pydantic (>=1.8.2)
Requires-Dist: pypinyin (>=0.54.0) ; python_version >= "3.11" and python_version < "4"
Requires-Dist: python-dotenv (>=0.19.0)
Requires-Dist: python-multipart (>=0.0.5)
Requires-Dist: soundfile (>=0.12.1)
Requires-Dist: torch (>=2.0.0)
Requires-Dist: torchaudio (>=2.0.0,<2.2.2)
Requires-Dist: transformers (>=4.30.0,<4.31.0)
Requires-Dist: uvicorn (>=0.15.0)
